logquery
