Metadata-Version: 2.1
Name: logquery
Version: 0.2.5
Summary: Tool for logging ZSQL and SQLAlchemy queries
Home-page: UNKNOWN
Author: CK <ch.kr.email@gmail.com>
License: GNU General Public License (GPL) v3
Platform: UNKNOWN
Classifier: Development Status :: 4 - Beta
Classifier: Environment :: Other Environment
Classifier: Framework :: Zope2
Classifier: Intended Audience :: Developers
Classifier: Programming Language :: Python
Classifier: Programming Language :: Python :: 2.7
Classifier: Topic :: System :: Logging
Classifier: Topic :: Software Development :: Libraries :: Python Modules
Provides-Extra: dev
